{"cameraMode":{"drawMode":0,"name":"Shaded","section":"Shading Mode"},"sceneLighting":true,"audioPlay":false,"sceneViewState":{"showFog":true,"showMaterialUpdate":false,"showSkybox":true,"showFlares":true,"showImageEffects":true,"showParticleSystems":true,"showVisualEffectGraphs":true,"m_FxEnabled":true},"in2DMode":false,"pivot":{"x":37.606117248535159,"y":3.89033842086792,"z":7.60901403427124},"rotation":{"x":0.10144288092851639,"y":0.33729052543640139,"z":-0.04187808185815811,"w":0.93547523021698},"size":23.25501823425293,"orthographic":false}